aihubcli/__init__.py
aihubcli/__main__.py
aihubcli/creator.py
aihubcli/templates/default.zip
aihubcli-1.0.1.dist-info/METADATA
aihubcli-1.0.1.dist-info/WHEEL
aihubcli-1.0.1.dist-info/dependency_links.txt
aihubcli-1.0.1.dist-info/entry_points.txt
aihubcli-1.0.1.dist-info/top_level.txt
aihubcli-1.0.1.dist-info/RECORD
