Metadata-Version: 2.1
Name: aihubcli
Version: 1.0.1
Summary: A simple cli utility to generate ML project structure for quickly starting ML projects
Home-page: UNKNOWN
Author: Vikram Soni
Author-email: vikram9880@gmail.com
License: MIT
Platform: UNKNOWN
Classifier: License :: OSI Approved :: MIT License
Classifier: Programming Language :: Python :: 2.7
Classifier: Programming Language :: Python :: 3
Classifier: Programming Language :: Python :: 3.7
Requires-Python: >=2.7
Requires-Dist: click
Requires-Dist: importlib-resources
